{"title":"The SpongeBob Movie Sponge Out Of Water 2015 HDRip XviD AC3-EVO","uid":11941934,"size":1503765046,"categoryP":"video","categoryS":"movies","magnet":"?xt=urn:btih:008f11c6693c041c92770863fb5500f3b1e59d69&amp;dn=The+SpongeBob+Movie+Sponge+Out+Of+Water+2015+HDRip+XviD+AC3-EVO&amp;tr=udp%3A%2F%2Ftracker.openbittorrent.com%3A80&amp;tr=udp%3A%2F%2Fopen.demonii.com%3A1337&amp;tr=udp%3A%2F%2Ftracker.coppersurfer.tk%3A6969&amp;tr=udp%3A%2F%2Fexodus.desync.com%3A6969","seeders":16,"leechers":5,"uploader":"xxxlavalxxx","files":4,"time":1431985900,"description":" &lt;a href=&quot;http://extraimago.com/image/NiB&quot; rel=&quot;nofollow&quot; target=&quot;_NEW&quot;&gt;http://extraimago.com/image/NiB&lt;/a&gt;\n &lt;a href=&quot;\nhttp://www.imdb.com/title/tt2279373/&quot; rel=&quot;nofollow&quot; target=&quot;_NEW&quot;&gt;\nhttp://www.imdb.com/title/tt2279373/&lt;/a&gt;\n\n\nWhen a diabolical pirate above the sea steals the secret Krabby Patty formula, SpongeBob and his nemesis Plankton must team up in order to get it back.\n\nDirector: Paul Tibbitt\nWriters: Glenn Berger (screenplay), Jonathan Aibel (screenplay)\nStars: Tom Kenny, Antonio Banderas, Bill Fagerbakke\nGenres: Animation | Adventure | Comedy | Family\nCountry: USA\nLanguage: English\n\n\nRELEASE: The.SpongeBob.Movie.Sponge.Out.Of.Water.2015.HDRip.XviD.AC3-EVO                                             \n\n SOURCE: 720p RUS - Thanks! (iTunes)                                              \n\n ViDEO: 1850 kbps XviD               \n\n RESOLUTiON: 720x400                          \n\n RUNTiME: 1h32m33sec      \n\n SUBTiTLES: No. (Clean)                               \n\n AUDiO: 256 CBR AC-3        \n\n LANGUAGE: ENGLiSH                                    \n\n GREETS: Srkfan &amp; AQOS \n \n NOTES: No subtitles hardcoded, clean version. Enjoy.   \n &lt;a href=&quot;\nhttp://extraimago.com/image/Ney&quot; rel=&quot;nofollow&quot; target=&quot;_NEW&quot;&gt;\nhttp://extraimago.com/image/Ney&lt;/a&gt; &lt;a href=&quot;\nhttp://extraimago.com/image/NeL&quot; rel=&quot;nofollow&quot; target=&quot;_NEW&quot;&gt;\nhttp://extraimago.com/image/NeL&lt;/a&gt; &lt;a href=&quot;\nhttp://extraimago.com/image/NeQ&quot; rel=&quot;nofollow&quot; target=&quot;_NEW&quot;&gt;\nhttp://extraimago.com/image/NeQ&lt;/a&gt; &lt;a href=&quot;\nhttp://extraimago.com/image/NeR&quot; rel=&quot;nofollow&quot; target=&quot;_NEW&quot;&gt;\nhttp://extraimago.com/image/NeR&lt;/a&gt; &lt;a href=&quot;\nhttp://extraimago.com/image/Nem&quot; rel=&quot;nofollow&quot; target=&quot;_NEW&quot;&gt;\nhttp://extraimago.com/image/Nem&lt;/a&gt; &lt;a href=&quot;\nhttp://extraimago.com/image/Nei&quot; rel=&quot;nofollow&quot; target=&quot;_NEW&quot;&gt;\nhttp://extraimago.com/image/Nei&lt;/a&gt;","torrent":{"xt":"urn:btih:008f11c6693c041c92770863fb5500f3b1e59d69","amp;dn":"The+SpongeBob+Movie+Sponge+Out+Of+Water+2015+HDRip+XviD+AC3-EVO","amp;tr":["udp%3A%2F%2Ftracker.openbittorrent.com%3A80","udp%3A%2F%2Fopen.demonii.com%3A1337","udp%3A%2F%2Ftracker.coppersurfer.tk%3A6969","udp%3A%2F%2Fexodus.desync.com%3A6969"],"infoHash":"008f11c6693c041c92770863fb5500f3b1e59d69","infoHashBuffer":{"type":"Buffer","data":[0,143,17,198,105,60,4,28,146,119,8,99,251,85,0,243,177,229,157,105]},"announce":[],"urlList":[]}}