{"title":"A State in Denial: Pakistan's Misguided and Dangerous Crusade","uid":15655425,"size":1721391,"categoryP":"other","categoryS":"e_books","magnet":"?xt=urn:btih:08bf2b86e3443ba982d5440c53b839cdbcbc4d9c&amp;dn=A+State+in+Denial%3A+Pakistan%27s+Misguided+and+Dangerous+Crusade+&amp;tr=udp%3A%2F%2Ftracker.leechers-paradise.org%3A6969&amp;tr=udp%3A%2F%2Fzer0day.ch%3A1337&amp;tr=udp%3A%2F%2Fopen.demonii.com%3A1337&amp;tr=udp%3A%2F%2Ftracker.coppersurfer.tk%3A6969&amp;tr=udp%3A%2F%2Fexodus.desync.com%3A6969","seeders":17,"leechers":2,"uploader":"Horisarte","files":4,"time":1472135305,"description":"http://www.amazon.in/Denial-Pakistans-Misguided-Dangerous-Crusade/dp/8129135981\r\n\r\nHardcover: 240 pages\r\nPublisher: Rupa Publications India; First edition (28 January 2016)\r\nLanguage: English\r\nISBN-10: 8129135981\r\nISBN-13: 978-8129135988","torrent":{"xt":"urn:btih:08bf2b86e3443ba982d5440c53b839cdbcbc4d9c","amp;dn":"A+State+in+Denial%3A+Pakistan%27s+Misguided+and+Dangerous+Crusade+","amp;tr":["udp%3A%2F%2Ftracker.leechers-paradise.org%3A6969","udp%3A%2F%2Fzer0day.ch%3A1337","udp%3A%2F%2Fopen.demonii.com%3A1337","udp%3A%2F%2Ftracker.coppersurfer.tk%3A6969","udp%3A%2F%2Fexodus.desync.com%3A6969"],"infoHash":"08bf2b86e3443ba982d5440c53b839cdbcbc4d9c","infoHashBuffer":{"type":"Buffer","data":[8,191,43,134,227,68,59,169,130,213,68,12,83,184,57,205,188,188,77,156]},"announce":[],"urlList":[]}}