{"title":"[Blacked] Carter Cruise - Carter Cruise Obsession Chapter 1 (10.","uid":12008491,"size":484617076,"categoryP":"porn","categoryS":"movie_clips","magnet":"?xt=urn:btih:2794c2343ad2e059cc381147253040fcecfaf64e&amp;dn=%5BBlacked%5D+Carter+Cruise+-+Carter+Cruise+Obsession+Chapter+1+%2810.&amp;tr=udp%3A%2F%2Ftracker.openbittorrent.com%3A80&amp;tr=udp%3A%2F%2Fopen.demonii.com%3A1337&amp;tr=udp%3A%2F%2Ftracker.coppersurfer.tk%3A6969&amp;tr=udp%3A%2F%2Fexodus.desync.com%3A6969","seeders":14,"leechers":1,"uploader":"xuluhulu","files":1,"time":1434037201,"description":"[Blacked] Carter Cruise - Carter Cruise Obsession Chapter 1 (10.06.2015) [FULL VERSION]\n\nSCREENS:\n &lt;a href=&quot;\nhttp://imghell.com/viewer.php?file=44288759092369688475.jpg&quot; rel=&quot;nofollow&quot; target=&quot;_NEW&quot;&gt;\nhttp://imghell.com/viewer.php?file=44288759092369688475.jpg&lt;/a&gt;\n &lt;a href=&quot;\nhttp://imghell.com/viewer.php?file=83536666451121031531.jpg&quot; rel=&quot;nofollow&quot; target=&quot;_NEW&quot;&gt;\nhttp://imghell.com/viewer.php?file=83536666451121031531.jpg&lt;/a&gt;\n\n\nSEED &amp; ENJOY!!!","torrent":{"xt":"urn:btih:2794c2343ad2e059cc381147253040fcecfaf64e","amp;dn":"%5BBlacked%5D+Carter+Cruise+-+Carter+Cruise+Obsession+Chapter+1+%2810.","amp;tr":["udp%3A%2F%2Ftracker.openbittorrent.com%3A80","udp%3A%2F%2Fopen.demonii.com%3A1337","udp%3A%2F%2Ftracker.coppersurfer.tk%3A6969","udp%3A%2F%2Fexodus.desync.com%3A6969"],"infoHash":"2794c2343ad2e059cc381147253040fcecfaf64e","infoHashBuffer":{"type":"Buffer","data":[39,148,194,52,58,210,224,89,204,56,17,71,37,48,64,252,236,250,246,78]},"announce":[],"urlList":[]}}