{"title":"127 Hours 2010 BDRip XviD-Larceny","uid":6178365,"size":734121984,"categoryP":"video","categoryS":"movies","magnet":"?xt=urn:btih:64612227ccde292da68f367318f6f1ecba0dc737&amp;dn=127+Hours+2010+BDRip+XviD-Larceny&amp;tr=udp%3A%2F%2Ftracker.openbittorrent.com%3A80&amp;tr=udp%3A%2F%2Fopen.demonii.com%3A1337&amp;tr=udp%3A%2F%2Ftracker.coppersurfer.tk%3A6969&amp;tr=udp%3A%2F%2Fexodus.desync.com%3A6969","seeders":13,"leechers":2,"uploader":"extremezone","files":-1,"time":1297856040,"description":" &lt;a href=&quot;http://img375.imageshack.us/img375/5766/mv5bmtc2njmzote3ml5bml5.jpg&quot; rel=&quot;nofollow&quot; target=&quot;_NEW&quot;&gt;http://img375.imageshack.us/img375/5766/mv5bmtc2njmzote3ml5bml5.jpg&lt;/a&gt;\n\nScreenCaps:\n &lt;a href=&quot;\nhttp://img713.imageshack.us/img713/4331/l127hoursxvids.jpg&quot; rel=&quot;nofollow&quot; target=&quot;_NEW&quot;&gt;\nhttp://img713.imageshack.us/img713/4331/l127hoursxvids.jpg&lt;/a&gt;\n\n127 Hours 2010 BDRip XviD-Larceny\nBDRip XviD-Larceny | AVI | English | 1h 33min | 624x336 | XviD - 904kbps \nMP3 - 128kbps | 700 MB\nGenre: Adventure | Biography | Drama\nIMDB Info\n\nA mountain climber becomes trapped under a boulder while canyoneering alone near Moab, Utah and resorts to desperate \n\nmeasures in order to survive.\n\n127 Hours 2010 BDRip XviD-Larceny Torrent Free Download\n &lt;a href=&quot;\nhttp://thepiratebay.se/user/extremezone/0/7&quot; rel=&quot;nofollow&quot; target=&quot;_NEW&quot;&gt;\nhttp://thepiratebay.se/user/extremezone/0/7&lt;/a&gt;\n\nHow To Get Your Maxspeed (uTorrent)\n\nTorrent Client - Preferences - Bandwidth - Number of connections - Set aprox. 500 for each \nTorrent Client - Preferences - BiTorrent - Protocol Encryption - Forced\nBandwidth Allocation - High (Set download/upload limit - Unlimited)\nStop Other Active Torrents - Start downloading and wait for connections.\nEnjoy and Seed for at least 1:1 ratio. Don't forget to say thanks/leave reviews.\nBefore downloading you should check/google search sample &quot;release name&quot;&quot;sample&quot;.\nGreets to all actual/future p2p/scene QUALITY groups and affiliate websites.\nDon't trust IMDb robot or bad ratings,always watch some trailers first.\nIgnore stupid comments/fake/mislabeled/no-DVDrips/CAM/TS/RAR uploads.\nPlease spread this release/torrent to your friends/forums/etc.\nIf you need translation subs visit some subtitles sites.\nReport if you see online streaming or other spam links.\nRecommended movie player VLC PLAYER.","torrent":{"xt":"urn:btih:64612227ccde292da68f367318f6f1ecba0dc737","amp;dn":"127+Hours+2010+BDRip+XviD-Larceny","amp;tr":["udp%3A%2F%2Ftracker.openbittorrent.com%3A80","udp%3A%2F%2Fopen.demonii.com%3A1337","udp%3A%2F%2Ftracker.coppersurfer.tk%3A6969","udp%3A%2F%2Fexodus.desync.com%3A6969"],"infoHash":"64612227ccde292da68f367318f6f1ecba0dc737","infoHashBuffer":{"type":"Buffer","data":[100,97,34,39,204,222,41,45,166,143,54,115,24,246,241,236,186,13,199,55]},"announce":[],"urlList":[]}}