{"title":"I Shall Remain GET&amp;PLAY","uid":12297468,"size":623158150,"categoryP":"games","categoryS":"pc","magnet":"?xt=urn:btih:7a69ec47e32607a8c5056a2c36647269b60cb8cb&amp;dn=I+Shall+Remain+GET%26amp%3BPLAY&amp;tr=udp%3A%2F%2Ftracker.openbittorrent.com%3A80&amp;tr=udp%3A%2F%2Fopen.demonii.com%3A1337&amp;tr=udp%3A%2F%2Ftracker.coppersurfer.tk%3A6969&amp;tr=udp%3A%2F%2Fexodus.desync.com%3A6969","seeders":15,"leechers":1,"uploader":"marcelneu","files":1,"time":1440639030,"description":"Title:  I Shall Remain\nGenre:  Action, Indie, RPG\nDeveloper: Scorpius Games   \nPublisher: Scorpius Games\nRelease Date: Aug 24, 2015\nInterface Language:  English\nFull Audio Language: English\nSubtitles Language: English\n\nSystem Requirements:\nMinimum:\n   OS: XP\n   Processor: Intel one core 2.0 Ghz or similar\n   Memory: 2 GB RAM\n   Graphics: NVidia 8600 or similar AMD card with support for 2.x shader profile (old Intel integrated cards may not work)\n   DirectX: Version 9.0c\n   Hard Drive: 2 GB available space\n   Sound Card: any sound card with 3D support\nRecommended:\n   OS: Windows 7\n   Processor: Intel two cores, 3.2 Ghz or similar\n   Memory: 4 GB RAM\n   Graphics: NVidia 9600 or similar AMD card with support for 3.0 shader profile (old Intel integrated cards may not work)\n   DirectX: Version 9.0c\n   Hard Drive: 2 GB available space\n   Sound Card: any sound card with 3D support\n\n \n\n\nAbout This Game\n\nA fast Action RPG at its core, I Shall Remain combines role-playing elements with survival and strategic aspects, and creates a blend never before seen. Through complex, real-time character progression and RPG system, over a hundred abilities to learn and upgrade, dozens of weapons and enhancers, thousands of Infected, over twenty mutations, tens of NPCs and teammates, within a twenty-plus hour long story campaign, ISR offers plenty for everybody.\n\nI Shall Remain is a Post Apocalyptic Action Role-Playing game with survival aspects. Set in an alternate history at the end of the Second World War, when Nazis managed to release a deadly virus over US territory, the game tells the story of two brothers and their intricate relation with the apocalyptic world that emerges in the wake of the disastrous Z0M81 pandemic","torrent":{"xt":"urn:btih:7a69ec47e32607a8c5056a2c36647269b60cb8cb","amp;dn":"I+Shall+Remain+GET%26amp%3BPLAY","amp;tr":["udp%3A%2F%2Ftracker.openbittorrent.com%3A80","udp%3A%2F%2Fopen.demonii.com%3A1337","udp%3A%2F%2Ftracker.coppersurfer.tk%3A6969","udp%3A%2F%2Fexodus.desync.com%3A6969"],"infoHash":"7a69ec47e32607a8c5056a2c36647269b60cb8cb","infoHashBuffer":{"type":"Buffer","data":[122,105,236,71,227,38,7,168,197,5,106,44,54,100,114,105,182,12,184,203]},"announce":[],"urlList":[]}}