{"title":"Barfuss (2005) DVDRip x264 AC3-MED","uid":11589710,"size":1248623529,"categoryP":"video","categoryS":"movies","magnet":"?xt=urn:btih:7fbe08f1f54119c8fbe4350b9c10ab5c5fb8fab2&amp;dn=Barfuss+%282005%29+DVDRip+x264+AC3-MED&amp;tr=udp%3A%2F%2Ftracker.openbittorrent.com%3A80&amp;tr=udp%3A%2F%2Fopen.demonii.com%3A1337&amp;tr=udp%3A%2F%2Ftracker.coppersurfer.tk%3A6969&amp;tr=udp%3A%2F%2Fexodus.desync.com%3A6969","seeders":16,"leechers":2,"uploader":"pBtu6RHs","files":-1,"time":1417216654,"description":"IMDB RATING.........: 7,2\nFORMAT..............: Mkv\nCODEC...............: x264\nGENRE...............: Comedy | Drama | Romance\nFILE SIZE...........: 1.16 GiB\nRESOLUTION..........: 704x432\nFRAME RATE..........: 25 Fps\nAUDIO...............: German 6 Ch AC-3\nSUBTITLES...........: English | Russian | Turkish\nLANGUAGE............: German\nRUNTIME.............: 118 min\n\nNick, a hedonistic bachelor, falls for an escaped mental patient.\n\nDirector: Til Schweiger\nWriters: Til Schweiger, Jann Preuss\nStars: Hans-Peter Abts, Gustav Adolph, Micha Breidenstein","torrent":{"xt":"urn:btih:7fbe08f1f54119c8fbe4350b9c10ab5c5fb8fab2","amp;dn":"Barfuss+%282005%29+DVDRip+x264+AC3-MED","amp;tr":["udp%3A%2F%2Ftracker.openbittorrent.com%3A80","udp%3A%2F%2Fopen.demonii.com%3A1337","udp%3A%2F%2Ftracker.coppersurfer.tk%3A6969","udp%3A%2F%2Fexodus.desync.com%3A6969"],"infoHash":"7fbe08f1f54119c8fbe4350b9c10ab5c5fb8fab2","infoHashBuffer":{"type":"Buffer","data":[127,190,8,241,245,65,25,200,251,228,53,11,156,16,171,92,95,184,250,178]},"announce":[],"urlList":[]}}