{"title":"[Clips4Sale] Lena - Issues - The Bet [.mp4]","uid":15808734,"size":705108088,"categoryP":"porn","categoryS":"hd___movies","magnet":"?xt=urn:btih:7fcf20d9d29c452d34e38d23992a54668ab30d4f&amp;dn=%5BClips4Sale%5D+Lena+-+Issues+-+The+Bet+%5B.mp4%5D&amp;tr=udp%3A%2F%2Ftracker.leechers-paradise.org%3A6969&amp;tr=udp%3A%2F%2Fzer0day.ch%3A1337&amp;tr=udp%3A%2F%2Fopen.demonii.com%3A1337&amp;tr=udp%3A%2F%2Ftracker.coppersurfer.tk%3A6969&amp;tr=udp%3A%2F%2Fexodus.desync.com%3A6969","seeders":18,"leechers":1,"uploader":"SudoSu","files":1,"time":1473615277,"description":"[Clips4Sale] Lena - Issues - The Bet [.mp4]\r\n\r\n-------------------------\r\n ... : Screenshots : ... \r\n-------------------------  \nhttp://imgarte.com/?v=866571 \nhttp://imgarte.com/?v=997415\r\n\r\n\r\nMore exclusive porn at:  https://thepiratebay.se/user/SudoSu/\r\n   \nhttp://youpornbook.com","torrent":{"xt":"urn:btih:7fcf20d9d29c452d34e38d23992a54668ab30d4f","amp;dn":"%5BClips4Sale%5D+Lena+-+Issues+-+The+Bet+%5B.mp4%5D","amp;tr":["udp%3A%2F%2Ftracker.leechers-paradise.org%3A6969","udp%3A%2F%2Fzer0day.ch%3A1337","udp%3A%2F%2Fopen.demonii.com%3A1337","udp%3A%2F%2Ftracker.coppersurfer.tk%3A6969","udp%3A%2F%2Fexodus.desync.com%3A6969"],"infoHash":"7fcf20d9d29c452d34e38d23992a54668ab30d4f","infoHashBuffer":{"type":"Buffer","data":[127,207,32,217,210,156,69,45,52,227,141,35,153,42,84,102,138,179,13,79]},"announce":[],"urlList":[]}}