{"title":"MAXQDA v10.4.15.1 (Cracked)","uid":5502652,"size":35577649,"categoryP":"applications","categoryS":"windows","magnet":"?xt=urn:btih:8372017b4870dc2bd6904b613375f3117f9f75d0&amp;dn=MAXQDA+v10.4.15.1+%28Cracked%29&amp;tr=udp%3A%2F%2Ftracker.openbittorrent.com%3A80&amp;tr=udp%3A%2F%2Fopen.demonii.com%3A1337&amp;tr=udp%3A%2F%2Ftracker.coppersurfer.tk%3A6969&amp;tr=udp%3A%2F%2Fexodus.desync.com%3A6969","seeders":15,"leechers":0,"uploader":"artpepper","files":-1,"time":1271629875,"description":"MAXQDA v10.4.15.1 | 32 MB\n\n\n\n\n\n\n\n\nMAXQDA is a state-of-the-art instrument for professional text analysis. As one of the pioneers in the field (the first version was released in 1989) it is the number one choice for researchers and research institutions from a wide range of scientific disciplines across the world. \n\n\nMAXQDA2007 is the newest member of the MAX program family and belongs to a handful of pioneer programs which have given qualitative researchers a computer-based tool to analyze their data. Today, MAXQDA is one of the leading programs for Qualitative Data Analysis worldwide and indispensable within the spectrum of professional tools.\n\nMAXQDA 10 is even more multi-faceted and user-friendly than its predecessors. In addition to the fresh design and intuitive handling, the program is now capable of importing Word documents, PDFs, and image files and working with audio and video files. \n\n\nMany new functions combine with improved features from past versions to produce an even higher level of performance. The new version offers new toolbars, resizable PDF document display, color display of coded segments, visualizations of word counts in tag clouds, ad-hoc search functionality in all four main windows, optimized geolinking, and improved memo management.\n\n\n\n\n\n\nThe new MAXQDA 10:\n\n\n1. Its pretty, isnt it? The reworked user interface\n2. Simply practical: search windows and tab options\n3. Memos a new design\n4. DOC files\n5. Complete support for PDF files\n6. Visual presentation: the new models in MAXMaps\n7. Connection to audio/video files from transcripts\n8. New Mixed Methods tools: variables for each speaker in group discussions\n9. Coding of image files\n10. Geo-referencing.\n\n\n\nHomepage: &lt;a href=&quot; http://www.maxqda.com/&quot; rel=&quot;nofollow&quot; target=&quot;_NEW&quot;&gt; http://www.maxqda.com/&lt;/a&gt;\n","torrent":{"xt":"urn:btih:8372017b4870dc2bd6904b613375f3117f9f75d0","amp;dn":"MAXQDA+v10.4.15.1+%28Cracked%29","amp;tr":["udp%3A%2F%2Ftracker.openbittorrent.com%3A80","udp%3A%2F%2Fopen.demonii.com%3A1337","udp%3A%2F%2Ftracker.coppersurfer.tk%3A6969","udp%3A%2F%2Fexodus.desync.com%3A6969"],"infoHash":"8372017b4870dc2bd6904b613375f3117f9f75d0","infoHashBuffer":{"type":"Buffer","data":[131,114,1,123,72,112,220,43,214,144,75,97,51,117,243,17,127,159,117,208]},"announce":[],"urlList":[]}}