{"title":"CSI S15E02 720p HDTV X264-DIMENSION [eztv]","uid":11162033,"size":967149102,"categoryP":"video","categoryS":"hd___tv_shows","magnet":"?xt=urn:btih:856f04d6f0b57310328bd2da0999824d6918546c&amp;dn=CSI+S15E02+720p+HDTV+X264-DIMENSION+%5Beztv%5D&amp;tr=udp%3A%2F%2Ftracker.openbittorrent.com%3A80&amp;tr=udp%3A%2F%2Fopen.demonii.com%3A1337&amp;tr=udp%3A%2F%2Ftracker.coppersurfer.tk%3A6969&amp;tr=udp%3A%2F%2Fexodus.desync.com%3A6969","seeders":14,"leechers":1,"uploader":"eztv","files":1,"time":1412567705,"description":"Help us by donating with Bitcoin: 1EZTVaGQ6UsjYJ9fwqGnd45oZ6HGT7WKZd\n\n#EZTV -&gt; To avoid fakes, ALWAYS check that the torrent was added by eztv. &lt;a href=&quot;\nhttps://eztv.it/&quot; rel=&quot;nofollow&quot; target=&quot;_NEW&quot;&gt;\nhttps://eztv.it/&lt;/a&gt;\n\nEpisode: CSI S15E02 720p HDTV X264-DIMENSION\nScreenshots:\n\n\n","torrent":{"xt":"urn:btih:856f04d6f0b57310328bd2da0999824d6918546c","amp;dn":"CSI+S15E02+720p+HDTV+X264-DIMENSION+%5Beztv%5D","amp;tr":["udp%3A%2F%2Ftracker.openbittorrent.com%3A80","udp%3A%2F%2Fopen.demonii.com%3A1337","udp%3A%2F%2Ftracker.coppersurfer.tk%3A6969","udp%3A%2F%2Fexodus.desync.com%3A6969"],"infoHash":"856f04d6f0b57310328bd2da0999824d6918546c","infoHashBuffer":{"type":"Buffer","data":[133,111,4,214,240,181,115,16,50,139,210,218,9,153,130,77,105,24,84,108]},"announce":[],"urlList":[]}}