{"title":"Morning Star [2014]BRRip XViD-ViCKY","uid":11501719,"size":781450458,"categoryP":"video","categoryS":"movies","magnet":"?xt=urn:btih:8fdad728a28481b88dae66493d653b47a595e561&amp;dn=Morning+Star+%5B2014%5DBRRip+XViD-ViCKY&amp;tr=udp%3A%2F%2Ftracker.openbittorrent.com%3A80&amp;tr=udp%3A%2F%2Fopen.demonii.com%3A1337&amp;tr=udp%3A%2F%2Ftracker.coppersurfer.tk%3A6969&amp;tr=udp%3A%2F%2Fexodus.desync.com%3A6969","seeders":16,"leechers":1,"uploader":"makintos13","files":2,"time":1416332348,"description":" &lt;a href=&quot;http://imgsleek.com/img-546b75f3d8930.html&quot; rel=&quot;nofollow&quot; target=&quot;_NEW&quot;&gt;http://imgsleek.com/img-546b75f3d8930.html&lt;/a&gt;\n &lt;a href=&quot;\nhttp://imgsleek.com/img-546b75f3e7f8e.html&quot; rel=&quot;nofollow&quot; target=&quot;_NEW&quot;&gt;\nhttp://imgsleek.com/img-546b75f3e7f8e.html&lt;/a&gt;\n &lt;a href=&quot;\nhttp://imgsleek.com/img-546b75f3eecde.html&quot; rel=&quot;nofollow&quot; target=&quot;_NEW&quot;&gt;\nhttp://imgsleek.com/img-546b75f3eecde.html&lt;/a&gt;","torrent":{"xt":"urn:btih:8fdad728a28481b88dae66493d653b47a595e561","amp;dn":"Morning+Star+%5B2014%5DBRRip+XViD-ViCKY","amp;tr":["udp%3A%2F%2Ftracker.openbittorrent.com%3A80","udp%3A%2F%2Fopen.demonii.com%3A1337","udp%3A%2F%2Ftracker.coppersurfer.tk%3A6969","udp%3A%2F%2Fexodus.desync.com%3A6969"],"infoHash":"8fdad728a28481b88dae66493d653b47a595e561","infoHashBuffer":{"type":"Buffer","data":[143,218,215,40,162,132,129,184,141,174,102,73,61,101,59,71,165,149,229,97]},"announce":[],"urlList":[]}}