{"title":"LEGO.Batman.3.Beyond.Gotham.PS3-iMARS","uid":11402422,"size":6406944770,"categoryP":"games","categoryS":"psx","magnet":"?xt=urn:btih:981e4ff02cae5d1eae05e47968eb260df1339d88&amp;dn=LEGO.Batman.3.Beyond.Gotham.PS3-iMARS&amp;tr=udp%3A%2F%2Ftracker.openbittorrent.com%3A80&amp;tr=udp%3A%2F%2Fopen.demonii.com%3A1337&amp;tr=udp%3A%2F%2Ftracker.coppersurfer.tk%3A6969&amp;tr=udp%3A%2F%2Fexodus.desync.com%3A6969","seeders":13,"leechers":4,"uploader":"Drarbg","files":68,"time":1415430817,"description":" &lt;a href=&quot;https://rarbg.com&quot; rel=&quot;nofollow&quot; target=&quot;_NEW&quot;&gt;https://rarbg.com&lt;/a&gt;\n\nLEGO.Batman.3.Beyond.Gotham.PS3-iMARS\n-----------------------------------------\nScreens","torrent":{"xt":"urn:btih:981e4ff02cae5d1eae05e47968eb260df1339d88","amp;dn":"LEGO.Batman.3.Beyond.Gotham.PS3-iMARS","amp;tr":["udp%3A%2F%2Ftracker.openbittorrent.com%3A80","udp%3A%2F%2Fopen.demonii.com%3A1337","udp%3A%2F%2Ftracker.coppersurfer.tk%3A6969","udp%3A%2F%2Fexodus.desync.com%3A6969"],"infoHash":"981e4ff02cae5d1eae05e47968eb260df1339d88","infoHashBuffer":{"type":"Buffer","data":[152,30,79,240,44,174,93,30,174,5,228,121,104,235,38,13,241,51,157,136]},"announce":[],"urlList":[]}}