{"title":"Tonight Alive - What Are You So Scared Of?","uid":6746495,"size":98350694,"categoryP":"audio","categoryS":"music","magnet":"?xt=urn:btih:9ade2a776542042512902f4e2f96f5ef8b836d7d&amp;dn=Tonight+Alive+-+What+Are+You+So+Scared+Of%3F&amp;tr=udp%3A%2F%2Ftracker.openbittorrent.com%3A80&amp;tr=udp%3A%2F%2Fopen.demonii.com%3A1337&amp;tr=udp%3A%2F%2Ftracker.coppersurfer.tk%3A6969&amp;tr=udp%3A%2F%2Fexodus.desync.com%3A6969","seeders":16,"leechers":0,"uploader":"gazza-911","files":14,"time":1318711008,"description":"Full Album by 'Tonight Alive' Credit goes to Matheus (I got this from a file sharing site). Variable bitrate: 230-260kb/s","torrent":{"xt":"urn:btih:9ade2a776542042512902f4e2f96f5ef8b836d7d","amp;dn":"Tonight+Alive+-+What+Are+You+So+Scared+Of%3F","amp;tr":["udp%3A%2F%2Ftracker.openbittorrent.com%3A80","udp%3A%2F%2Fopen.demonii.com%3A1337","udp%3A%2F%2Ftracker.coppersurfer.tk%3A6969","udp%3A%2F%2Fexodus.desync.com%3A6969"],"infoHash":"9ade2a776542042512902f4e2f96f5ef8b836d7d","infoHashBuffer":{"type":"Buffer","data":[154,222,42,119,101,66,4,37,18,144,47,78,47,150,245,239,139,131,109,125]},"announce":[],"urlList":[]}}