{"title":"Frank Zappa - Official Discography, Part 2 (1971-1976)","uid":13405488,"size":1002133330,"categoryP":"audio","categoryS":"music","magnet":"?xt=urn:btih:9bd0ac48d9cfe0a6cc117741d07269791f15ca94&amp;dn=Frank+Zappa+-+Official+Discography%2C+Part+2+%281971-1976%29&amp;tr=udp%3A%2F%2Ftracker.leechers-paradise.org%3A6969&amp;tr=udp%3A%2F%2Fzer0day.ch%3A1337&amp;tr=udp%3A%2F%2Fopen.demonii.com%3A1337&amp;tr=udp%3A%2F%2Ftracker.coppersurfer.tk%3A6969&amp;tr=udp%3A%2F%2Fexodus.desync.com%3A6969","seeders":18,"leechers":5,"uploader":"Drebben","files":140,"time":1454431799,"description":"Frank Zappa\r\n\r\n&amp; The Mothers of Invention\r\n\r\n&amp; Captain Beefheart\r\n\r\n\r\nOfficial Discography:\r\n\r\nPart 2\r\n\r\n1971-1976\r\n\r\n#12-22\r\n\r\n\r\nRemasters / Analog Masters\r\n\r\n\r\n#12 Fillmore East, June 1971 (August 1971)\r\n\r\n#13 200 Motels (October 1971) 2CD\r\n\r\n#14 Just Another Band From L.A. (March 1972)\r\n\r\n#15 Waka-Jawaka (July 1972)\r\n\r\n#16 The Grand Wazoo (November 1972)\r\n\r\n#17 Over-Nite Sensation (September 1973)\r\n\r\n#18 Apostrophe (') (March 1974)\r\n\r\n#19 Roxy &amp; Elsewhere (July 1974)\r\n\r\n#20 One Size Fits All (June 1975)\r\n\r\n#21 Bongo Fury (October 1975)\r\n\r\n#22 Zoot Allures (October 1976)\r\n\r\n\r\n\r\n12CDs / 2012 / Remastered / VBR-V0\r\n\r\n\r\nClick 'Files' to see Track List\r\n\r\n\r\nTo be continued, Part 3 coming soon, stay tuned . . .\r\n\r\n\r\n:)","torrent":{"xt":"urn:btih:9bd0ac48d9cfe0a6cc117741d07269791f15ca94","amp;dn":"Frank+Zappa+-+Official+Discography%2C+Part+2+%281971-1976%29","amp;tr":["udp%3A%2F%2Ftracker.leechers-paradise.org%3A6969","udp%3A%2F%2Fzer0day.ch%3A1337","udp%3A%2F%2Fopen.demonii.com%3A1337","udp%3A%2F%2Ftracker.coppersurfer.tk%3A6969","udp%3A%2F%2Fexodus.desync.com%3A6969"],"infoHash":"9bd0ac48d9cfe0a6cc117741d07269791f15ca94","infoHashBuffer":{"type":"Buffer","data":[155,208,172,72,217,207,224,166,204,17,119,65,208,114,105,121,31,21,202,148]},"announce":[],"urlList":[]}}