{"title":"Stepmom Videos - Ava Adams and Daisy Haze (Stepdaughter And Step","uid":11798433,"size":507449417,"categoryP":"porn","categoryS":"movie_clips","magnet":"?xt=urn:btih:a808278d5ba1928b7b90fc2caaa52f7a65238f23&amp;dn=Stepmom+Videos+-+Ava+Adams+and+Daisy+Haze+%28Stepdaughter+And+Step&amp;tr=udp%3A%2F%2Ftracker.openbittorrent.com%3A80&amp;tr=udp%3A%2F%2Fopen.demonii.com%3A1337&amp;tr=udp%3A%2F%2Ftracker.coppersurfer.tk%3A6969&amp;tr=udp%3A%2F%2Fexodus.desync.com%3A6969","seeders":17,"leechers":3,"uploader":"ThousandPeers","files":1,"time":1428269518,"description":"Stepmom Videos - Ava Adams and Daisy Haze (Stepdaughter And Stepmom Fuck BF)\n\nScreens &amp; Info :\n\n----------------------------------\n &lt;a href=&quot;\nhttp://lovechix.com/?p=148650&quot; rel=&quot;nofollow&quot; target=&quot;_NEW&quot;&gt;\nhttp://lovechix.com/?p=148650&lt;/a&gt;\n &lt;a href=&quot;\nhttp://lovechix.com/?p=274242&quot; rel=&quot;nofollow&quot; target=&quot;_NEW&quot;&gt;\nhttp://lovechix.com/?p=274242&lt;/a&gt;\n\n----------------------------------\n\nBrowse my entire collection at:\n &lt;a href=&quot;\nhttps://thepiratebay.se/user/kymatica7/&quot; rel=&quot;nofollow&quot; target=&quot;_NEW&quot;&gt;\nhttps://thepiratebay.se/user/kymatica7/&lt;/a&gt;","torrent":{"xt":"urn:btih:a808278d5ba1928b7b90fc2caaa52f7a65238f23","amp;dn":"Stepmom+Videos+-+Ava+Adams+and+Daisy+Haze+%28Stepdaughter+And+Step","amp;tr":["udp%3A%2F%2Ftracker.openbittorrent.com%3A80","udp%3A%2F%2Fopen.demonii.com%3A1337","udp%3A%2F%2Ftracker.coppersurfer.tk%3A6969","udp%3A%2F%2Fexodus.desync.com%3A6969"],"infoHash":"a808278d5ba1928b7b90fc2caaa52f7a65238f23","infoHashBuffer":{"type":"Buffer","data":[168,8,39,141,91,161,146,139,123,144,252,44,170,165,47,122,101,35,143,35]},"announce":[],"urlList":[]}}