{"title":"Fight Club (1999) DVDRip XviD DivXNL-Team (nl subs)","uid":5641802,"size":736645121,"categoryP":"video","categoryS":"movies","magnet":"?xt=urn:btih:a97461b6da6be6f7a3dd40e086eef7aadecbc1e9&amp;dn=Fight+Club+%281999%29+DVDRip+XviD+DivXNL-Team+%28nl+subs%29&amp;tr=udp%3A%2F%2Ftracker.openbittorrent.com%3A80&amp;tr=udp%3A%2F%2Fopen.demonii.com%3A1337&amp;tr=udp%3A%2F%2Ftracker.coppersurfer.tk%3A6969&amp;tr=udp%3A%2F%2Fexodus.desync.com%3A6969","seeders":13,"leechers":0,"uploader":"smokey91","files":-1,"time":1277139731,"description":"Verenigde Staten / Duitsland\nKomedie / Thriller\n139 minuten\n\ngeregisseerd door David Fincher\nmet Edward Norton, Brad Pitt en Helena Bonham Carter\n\nHij is een verzekeringsinspecteur die aan chronische slapeloosheid lijdt, en die wanhopig probeert uit zijn oersaaie bestaan te ontsnappen. Bij toeval ontmoet hij Tyler Durden, een charismatische zeepverkoper met een bizarre levensfilosofie. Tyler gelooft namelijk dat &quot;zelfverbetering&quot; enkel voor de zwakken is, het is &quot;zelfvernieling&quot; die het leven meer waarde geeft. Samen met Tyler organiseert hij de ultieme vorm van ontspanning: zogeheten &quot;Fight Clubs&quot;, waar gewone jonge mannen het beest in zichzelf loslaten in blotevuistgevechten. Het bevrijdend effect op de deelnemende mannen doet een vreemd soort kameraadschap ontstaan, dat al snel gevaarlijke vormen aanneemt.\n\nfilm info: &lt;a href=&quot;\nhttp://www.moviemeter.nl/film/175&quot; rel=&quot;nofollow&quot; target=&quot;_NEW&quot;&gt;\nhttp://www.moviemeter.nl/film/175&lt;/a&gt; &lt;a href=&quot;\nhttp://www.imdb.com/title/tt0137523/&quot; rel=&quot;nofollow&quot; target=&quot;_NEW&quot;&gt;\nhttp://www.imdb.com/title/tt0137523/&lt;/a&gt;\n\n \n\nveel plezier ermee\n\nBezoek ons eens op:\n &lt;a href=&quot;\nhttp://www.divxnl-team.nl&quot; rel=&quot;nofollow&quot; target=&quot;_NEW&quot;&gt;\nhttp://www.divxnl-team.nl&lt;/a&gt;\n","torrent":{"xt":"urn:btih:a97461b6da6be6f7a3dd40e086eef7aadecbc1e9","amp;dn":"Fight+Club+%281999%29+DVDRip+XviD+DivXNL-Team+%28nl+subs%29","amp;tr":["udp%3A%2F%2Ftracker.openbittorrent.com%3A80","udp%3A%2F%2Fopen.demonii.com%3A1337","udp%3A%2F%2Ftracker.coppersurfer.tk%3A6969","udp%3A%2F%2Fexodus.desync.com%3A6969"],"infoHash":"a97461b6da6be6f7a3dd40e086eef7aadecbc1e9","infoHashBuffer":{"type":"Buffer","data":[169,116,97,182,218,107,230,247,163,221,64,224,134,238,247,170,222,203,193,233]},"announce":[],"urlList":[]}}