{"title":"Aerosmith - Tough Love - Best Of The Ballads - [TFM]","uid":8383455,"size":582192042,"categoryP":"audio","categoryS":"flac","magnet":"?xt=urn:btih:b2ea2a6f23006a88101a022bf1438215bd85efe4&amp;dn=Aerosmith+-+Tough+Love+-+Best+Of+The+Ballads+-+%5BTFM%5D&amp;tr=udp%3A%2F%2Ftracker.openbittorrent.com%3A80&amp;tr=udp%3A%2F%2Fopen.demonii.com%3A1337&amp;tr=udp%3A%2F%2Ftracker.coppersurfer.tk%3A6969&amp;tr=udp%3A%2F%2Fexodus.desync.com%3A6969","seeders":14,"leechers":11,"uploader":"tifon","files":-1,"time":1366225735,"description":"\n            Aerosmith - Tough Love - Best Of The Ballads\n\n\nArtist...............: Aerosmith\nAlbum................: Tough Love - Best Of The Ballads\nGenre................: Rock\nSource...............: CD\nYear.................: 2011\nRipper...............: EAC (Secure mode) / LAME 3.92 &amp; Samsung CDRW/DVD SH-S202J\nCodec................: Free Lossless Audio Codec (FLAC)\nVersion..............: reference libFLAC 1.2.0 20070715\nQuality..............: Lossless, (avg. compression: 70 %)\nChannels.............: Stereo / 44100 HZ / 16 Bit\nTags.................: VorbisComment\nInformation..........: \n\nRipped by............: [TFM] on 2013.04.17.\nPosted by............: [TFM] on 2013.04.17.\nNews Server..........: \nNews Group(s)........: ahashare.sounds.FLAC\n\nIncluded.............: NFO, M3U, LOG, CUE\nCovers...............: Front Back CD \n\n\n                       Tracklisting\n\n\n   1. Aerosmith - I Don't Want To Miss A Thing                [05:00]\n   2. Aerosmith - Angel                                       [05:08]\n   3. Aerosmith - Amazing                                     [05:34]\n   4. Aerosmith - Love In An Elevator                         [05:23]\n   5. Aerosmith - Pink                                        [03:56]\n   6. Aerosmith - Cryin'                                      [05:09]\n   7. Aerosmith - What It Takes                               [05:12]\n   8. Aerosmith - Rag Doll                                    [04:26]\n   9. Aerosmith - Crazy                                       [05:16]\n  10. Aerosmith - Deuces Are Wild                             [03:35]\n  11. Aerosmith - Livin' On The Edge                          [06:19]\n  12. Aerosmith - Blind Man                                   [03:58]\n  13. Aerosmith - Magic Touch                                 [04:38]\n  14. Aerosmith - Janie's Got A Gun                           [05:28]\n  15. Aerosmith - Sweet Emotion                               [04:38]\n  16. Aerosmith - Dream On                                    [04:28]\n\nPlaying Time.........: 01:18:16\nTotal Size...........: 553,68 MB","torrent":{"xt":"urn:btih:b2ea2a6f23006a88101a022bf1438215bd85efe4","amp;dn":"Aerosmith+-+Tough+Love+-+Best+Of+The+Ballads+-+%5BTFM%5D","amp;tr":["udp%3A%2F%2Ftracker.openbittorrent.com%3A80","udp%3A%2F%2Fopen.demonii.com%3A1337","udp%3A%2F%2Ftracker.coppersurfer.tk%3A6969","udp%3A%2F%2Fexodus.desync.com%3A6969"],"infoHash":"b2ea2a6f23006a88101a022bf1438215bd85efe4","infoHashBuffer":{"type":"Buffer","data":[178,234,42,111,35,0,106,136,16,26,2,43,241,67,130,21,189,133,239,228]},"announce":[],"urlList":[]}}