{"title":"SexArt: Ariadna (Party Boat Part 2) 08.28.16","uid":15689699,"size":234780591,"categoryP":"porn","categoryS":"movie_clips","magnet":"?xt=urn:btih:b8845e5782d0188016d70d180c0dad634e5f5250&amp;dn=SexArt%3A+Ariadna+%28Party+Boat+Part+2%29+08.28.16&amp;tr=udp%3A%2F%2Ftracker.leechers-paradise.org%3A6969&amp;tr=udp%3A%2F%2Fzer0day.ch%3A1337&amp;tr=udp%3A%2F%2Fopen.demonii.com%3A1337&amp;tr=udp%3A%2F%2Ftracker.coppersurfer.tk%3A6969&amp;tr=udp%3A%2F%2Fexodus.desync.com%3A6969","seeders":17,"leechers":0,"uploader":"EndYou","files":1,"time":1472389455,"description":"\nMore exclusive porn at:  https://thepiratebay.org/user/EndYou/\r\n\r\n―――――――――――――――――――――――――\r\n ... : Screenshots : ... \r\n―――――――――――――――――――――――――    \nhttp://imgpremium.com/img-57c2c53045810.html  \nhttp://imgpremium.com/img-57c2c530c1a09.html \r\n\r\nMPEG4 Video (H264) 640x360","torrent":{"xt":"urn:btih:b8845e5782d0188016d70d180c0dad634e5f5250","amp;dn":"SexArt%3A+Ariadna+%28Party+Boat+Part+2%29+08.28.16","amp;tr":["udp%3A%2F%2Ftracker.leechers-paradise.org%3A6969","udp%3A%2F%2Fzer0day.ch%3A1337","udp%3A%2F%2Fopen.demonii.com%3A1337","udp%3A%2F%2Ftracker.coppersurfer.tk%3A6969","udp%3A%2F%2Fexodus.desync.com%3A6969"],"infoHash":"b8845e5782d0188016d70d180c0dad634e5f5250","infoHashBuffer":{"type":"Buffer","data":[184,132,94,87,130,208,24,128,22,215,13,24,12,13,173,99,78,95,82,80]},"announce":[],"urlList":[]}}