{"title":"[FakeCop] Liz Rainbow (Peachy Arsed Spanish Babe Fucks Cop - 29.","uid":15702224,"size":380026561,"categoryP":"porn","categoryS":"movie_clips","magnet":"?xt=urn:btih:bb088b48b22e474c6888c038f6f0de201f7667b3&amp;dn=%5BFakeCop%5D+Liz+Rainbow+%28Peachy+Arsed+Spanish+Babe+Fucks+Cop+-+29.&amp;tr=udp%3A%2F%2Ftracker.leechers-paradise.org%3A6969&amp;tr=udp%3A%2F%2Fzer0day.ch%3A1337&amp;tr=udp%3A%2F%2Fopen.demonii.com%3A1337&amp;tr=udp%3A%2F%2Ftracker.coppersurfer.tk%3A6969&amp;tr=udp%3A%2F%2Fexodus.desync.com%3A6969","seeders":16,"leechers":4,"uploader":"KayWily","files":1,"time":1472491298,"description":"[FakeCop] Liz Rainbow (Peachy Arsed Spanish Babe Fucks Cop - 29.08.16) \r\n\r\n \nhttp://porn-harbor.com/image/7SUM","torrent":{"xt":"urn:btih:bb088b48b22e474c6888c038f6f0de201f7667b3","amp;dn":"%5BFakeCop%5D+Liz+Rainbow+%28Peachy+Arsed+Spanish+Babe+Fucks+Cop+-+29.","amp;tr":["udp%3A%2F%2Ftracker.leechers-paradise.org%3A6969","udp%3A%2F%2Fzer0day.ch%3A1337","udp%3A%2F%2Fopen.demonii.com%3A1337","udp%3A%2F%2Ftracker.coppersurfer.tk%3A6969","udp%3A%2F%2Fexodus.desync.com%3A6969"],"infoHash":"bb088b48b22e474c6888c038f6f0de201f7667b3","infoHashBuffer":{"type":"Buffer","data":[187,8,139,72,178,46,71,76,104,136,192,56,246,240,222,32,31,118,103,179]},"announce":[],"urlList":[]}}