{"title":"Pearl.Harbor[2001]DvDrip[Eng.Subs]-kirklestat","uid":3961273,"size":734028633,"categoryP":"video","categoryS":"movies","magnet":"?xt=urn:btih:bbc2691c833340fce0b86ee9ec77038288f30ad2&amp;dn=Pearl.Harbor%5B2001%5DDvDrip%5BEng.Subs%5D-kirklestat&amp;tr=udp%3A%2F%2Ftracker.openbittorrent.com%3A80&amp;tr=udp%3A%2F%2Fopen.demonii.com%3A1337&amp;tr=udp%3A%2F%2Ftracker.coppersurfer.tk%3A6969&amp;tr=udp%3A%2F%2Fexodus.desync.com%3A6969","seeders":18,"leechers":0,"uploader":"kirklestat","files":2,"time":1199467363,"description":"TITLE: Pearl Harbor\n\nRELEASE DATE: 6 June 2001 (USA)\n\nGENRE: Adventure / Drama / Romance / War\n\nFILE SIZE: 700 MB\n\nPLAYTIME: 02:55:35\n\nAUDIO:\nCodec: MP3\nBit rate: 96 Kbps\nBit rate mode: CBR\nChannel(s): 2 Channels\nSampling rate: 48 KHz\n\nVIDEO:\nCodec: XviD\nBit rate: 445 Kbps\nResolution: 540 x 220\nAspect ratio: 2.455\nFrame rate: 25.000 fps\nBits/(Pixel*Frame): 0.150\n\nSOURCE: PAL DVD\n\nPLOT OUTLINE: Pearl Harbor follows the story of two best friends, Rafe and Danny, and their love lives as they go off to join the war.","torrent":{"xt":"urn:btih:bbc2691c833340fce0b86ee9ec77038288f30ad2","amp;dn":"Pearl.Harbor%5B2001%5DDvDrip%5BEng.Subs%5D-kirklestat","amp;tr":["udp%3A%2F%2Ftracker.openbittorrent.com%3A80","udp%3A%2F%2Fopen.demonii.com%3A1337","udp%3A%2F%2Ftracker.coppersurfer.tk%3A6969","udp%3A%2F%2Fexodus.desync.com%3A6969"],"infoHash":"bbc2691c833340fce0b86ee9ec77038288f30ad2","infoHashBuffer":{"type":"Buffer","data":[187,194,105,28,131,51,64,252,224,184,110,233,236,119,3,130,136,243,10,210]},"announce":[],"urlList":[]}}