{"title":"Thelonius Monk The complete riverside recordings","uid":3496298,"size":1396805344,"categoryP":"audio","categoryS":"music","magnet":"?xt=urn:btih:bd250c87818311029c3d7858fd922705a480a8fa&amp;dn=Thelonius+Monk+The+complete+riverside+recordings&amp;tr=udp%3A%2F%2Ftracker.openbittorrent.com%3A80&amp;tr=udp%3A%2F%2Fopen.demonii.com%3A1337&amp;tr=udp%3A%2F%2Ftracker.coppersurfer.tk%3A6969&amp;tr=udp%3A%2F%2Fexodus.desync.com%3A6969","seeders":13,"leechers":1,"uploader":"silverleaf","files":169,"time":1150663163,"description":"The complete 15-cd set of Thelonius Monk&amp;#039;s Riverside recordings, including multiple takes, out-takes and many different arrangements of his classic jazz works.","torrent":{"xt":"urn:btih:bd250c87818311029c3d7858fd922705a480a8fa","amp;dn":"Thelonius+Monk+The+complete+riverside+recordings","amp;tr":["udp%3A%2F%2Ftracker.openbittorrent.com%3A80","udp%3A%2F%2Fopen.demonii.com%3A1337","udp%3A%2F%2Ftracker.coppersurfer.tk%3A6969","udp%3A%2F%2Fexodus.desync.com%3A6969"],"infoHash":"bd250c87818311029c3d7858fd922705a480a8fa","infoHashBuffer":{"type":"Buffer","data":[189,37,12,135,129,131,17,2,156,61,120,88,253,146,39,5,164,128,168,250]},"announce":[],"urlList":[]}}