{"title":"Jesse Livermore's Methods of Trading in Stocks (2012)","uid":11806581,"size":40307375,"categoryP":"audio","categoryS":"audio_books","magnet":"?xt=urn:btih:bd365078ceed1e57462514f7b03dd149495232cf&amp;dn=+Jesse+Livermore%27s+Methods+of+Trading+in+Stocks+%282012%29&amp;tr=udp%3A%2F%2Ftracker.openbittorrent.com%3A80&amp;tr=udp%3A%2F%2Fopen.demonii.com%3A1337&amp;tr=udp%3A%2F%2Ftracker.coppersurfer.tk%3A6969&amp;tr=udp%3A%2F%2Fexodus.desync.com%3A6969","seeders":14,"leechers":1,"uploader":"davieboy1966","files":3,"time":1428619280,"description":"Audio Books : Educational : Other quality : English\n\nThe material presented here first appeared as a continuing series of articles in the Magazine of Wall Street. They were obtained through exclusive interviews with Jesse Livermore by R.D. Wyckoff at a time when Livermore was the single most formidable factor in the market.\n\nAfter being &quot;lost&quot; for many years, these interviews are now brought together in book format.\n\nEnjoy and Seed!","torrent":{"xt":"urn:btih:bd365078ceed1e57462514f7b03dd149495232cf","amp;dn":"+Jesse+Livermore%27s+Methods+of+Trading+in+Stocks+%282012%29","amp;tr":["udp%3A%2F%2Ftracker.openbittorrent.com%3A80","udp%3A%2F%2Fopen.demonii.com%3A1337","udp%3A%2F%2Ftracker.coppersurfer.tk%3A6969","udp%3A%2F%2Fexodus.desync.com%3A6969"],"infoHash":"bd365078ceed1e57462514f7b03dd149495232cf","infoHashBuffer":{"type":"Buffer","data":[189,54,80,120,206,237,30,87,70,37,20,247,176,61,209,73,73,82,50,207]},"announce":[],"urlList":[]}}