{"title":"Agent Cody Banks 2003 DVDRip x264-HiGH","uid":7470500,"size":1592134185,"categoryP":"video","categoryS":"movies","magnet":"?xt=urn:btih:ce8dcd2f07b0fbd78e82345634b9b0895d66fac2&amp;dn=Agent+Cody+Banks+2003+DVDRip+x264-HiGH&amp;tr=udp%3A%2F%2Ftracker.openbittorrent.com%3A80&amp;tr=udp%3A%2F%2Fopen.demonii.com%3A1337&amp;tr=udp%3A%2F%2Ftracker.coppersurfer.tk%3A6969&amp;tr=udp%3A%2F%2Fexodus.desync.com%3A6969","seeders":18,"leechers":15,"uploader":"HiGH-RG","files":-1,"time":1343136335,"description":" &lt;a href=&quot;http://image.bayimg.com/jaabhaaee.jpg&quot; rel=&quot;nofollow&quot; target=&quot;_NEW&quot;&gt;http://image.bayimg.com/jaabhaaee.jpg&lt;/a&gt;\n\nHiGH iS PROUD TO\nPRESENT\n\nAgent.Cody.Banks.2003.DVDRip.x264-HiGH\n\nEncoder: sundox\nSource: Own\nSize: 1.47GB\niMDB Link: http://www.imdb.com/title/tt0313911/\niMDB Rating: 5.0\nGenre: Action | Adventure | Comedy\nRuntime: 97min\nSubtitle: None\nPlot: A government agent trains Cody Banks in the\nways of covert operations that require younger participants.\n\nMovie Information\n\nVideo:\nCodec: x264\nBitrate: 1698 Kbps\nFrame Rate: 25.000 fps\nResolution: 720x304\nAspect Ratio: 2.35:1\n\nAudio:\nCodec: AC-3\nBitrate: 448 Kbps\nChannel(s): 6 channels\nSampling: 48.0 KHz\n &lt;a href=&quot;\nhttp://image.bayimg.com/jaabiaaee.jpg&quot; rel=&quot;nofollow&quot; target=&quot;_NEW&quot;&gt;\nhttp://image.bayimg.com/jaabiaaee.jpg&lt;/a&gt; &lt;a href=&quot;\nhttp://image.bayimg.com/jaablaaee.jpg&quot; rel=&quot;nofollow&quot; target=&quot;_NEW&quot;&gt;\nhttp://image.bayimg.com/jaablaaee.jpg&lt;/a&gt; &lt;a href=&quot;\nhttp://image.bayimg.com/jaabmaaee.jpg&quot; rel=&quot;nofollow&quot; target=&quot;_NEW&quot;&gt;\nhttp://image.bayimg.com/jaabmaaee.jpg&lt;/a&gt;\n\nNotes\n\nGot anything to offer join us on irc\n#HiGH-RG @EFNet\n\nGreetings\n\nTo my fellow Encoders, politux,\nmiRaGe,INFERNO, Hive-CM8, 26k,\nINSPiRAL, Feel-Free, AXED, Noir\nand all other P2P groups :)\n &lt;a href=&quot;\nhttp://image.bayimg.com/dapehaadl.jpg&quot; rel=&quot;nofollow&quot; target=&quot;_NEW&quot;&gt;\nhttp://image.bayimg.com/dapehaadl.jpg&lt;/a&gt;","torrent":{"xt":"urn:btih:ce8dcd2f07b0fbd78e82345634b9b0895d66fac2","amp;dn":"Agent+Cody+Banks+2003+DVDRip+x264-HiGH","amp;tr":["udp%3A%2F%2Ftracker.openbittorrent.com%3A80","udp%3A%2F%2Fopen.demonii.com%3A1337","udp%3A%2F%2Ftracker.coppersurfer.tk%3A6969","udp%3A%2F%2Fexodus.desync.com%3A6969"],"infoHash":"ce8dcd2f07b0fbd78e82345634b9b0895d66fac2","infoHashBuffer":{"type":"Buffer","data":[206,141,205,47,7,176,251,215,142,130,52,86,52,185,176,137,93,102,250,194]},"announce":[],"urlList":[]}}