{"title":"[Trannies-Fuck] Mariana Fenix and Leticia Freitas Sexual Fun","uid":15978182,"size":521399109,"categoryP":"porn","categoryS":"movie_clips","magnet":"?xt=urn:btih:de423d8715977090f5a24552e54254772d7d8a5c&amp;dn=%5BTrannies-Fuck%5D+Mariana+Fenix+and+Leticia+Freitas+Sexual+Fun+&amp;tr=udp%3A%2F%2Ftracker.leechers-paradise.org%3A6969&amp;tr=udp%3A%2F%2Fzer0day.ch%3A1337&amp;tr=udp%3A%2F%2Fopen.demonii.com%3A1337&amp;tr=udp%3A%2F%2Ftracker.coppersurfer.tk%3A6969&amp;tr=udp%3A%2F%2Fexodus.desync.com%3A6969","seeders":14,"leechers":6,"uploader":"KayWily","files":1,"time":1475867054,"description":"[Trannies-Fuck] Mariana Fenix and Leticia Freitas Sexual Fun (12th June 2014)\r\n\r\n \nhttp://hotspic.ru/image/J6muM","torrent":{"xt":"urn:btih:de423d8715977090f5a24552e54254772d7d8a5c","amp;dn":"%5BTrannies-Fuck%5D+Mariana+Fenix+and+Leticia+Freitas+Sexual+Fun+","amp;tr":["udp%3A%2F%2Ftracker.leechers-paradise.org%3A6969","udp%3A%2F%2Fzer0day.ch%3A1337","udp%3A%2F%2Fopen.demonii.com%3A1337","udp%3A%2F%2Ftracker.coppersurfer.tk%3A6969","udp%3A%2F%2Fexodus.desync.com%3A6969"],"infoHash":"de423d8715977090f5a24552e54254772d7d8a5c","infoHashBuffer":{"type":"Buffer","data":[222,66,61,135,21,151,112,144,245,162,69,82,229,66,84,119,45,125,138,92]},"announce":[],"urlList":[]}}